{
  "items": [
    {
      "image": "/uploads/image-ldhs-cheque.jpg",
      "title": "LDHS Cheque Presenting"
    },
    {
      "image": "/uploads/image-fcss-cheque.jpg",
      "title": "FCSS Cheque Presenting"
    },
    {
      "image": "/uploads/image-ecovision-cheque.jpg",
      "title": "Ecovision Cheque Goat Barn"
    },
    {
      "image": "/uploads/image-christmas-parade.jpg",
      "title": "2021 Echo Christmas Parade"
    },
    {
      "image": "/uploads/image-terrace-ridge-garden.jpg",
      "title": "Terrace Ridge Garden"
    },
    {
      "image": "/uploads/image-stage-light-up.jpg",
      "title": "Light Up"
    },
    {
      "image": "/uploads/image-arena.jpg",
      "title": "Ice Complex Sponsorship"
    },
    {
      "image": "/uploads/image-food-bank.jpg",
      "title": "Food Bank Donation"
    },
    {
      "image": "/uploads/image-lure-1.jpg",
      "title": "Fishing Lure 1"
    },
    {
      "image": "/uploads/image-lure-2.jpg",
      "title": "Fishing Lure 2"
    },
    {
      "image": "/uploads/image-stones-edging.jpg",
      "title": "Painted Rock Edging"
    }
  ]
}
